file_system/__init__ .py
file_system/file_mcp_server.py
moggy_file_mcp-0.1.4.dist-info/METADATA
moggy_file_mcp-0.1.4.dist-info/WHEEL
moggy_file_mcp-0.1.4.dist-info/entry_points.txt
moggy_file_mcp-0.1.4.dist-info/RECORD
