Metadata-Version: 2.4
Name: moggy-file-mcp
Version: 0.1.4
Summary: Add your description here
Requires-Python: >=3.12
Requires-Dist: mcp[cli]>=1.6.0
